pytoniq_tools/__init__.py
pytoniq_tools/contract.py
pytoniq_tools/exceptions.py
pytoniq_tools/utils.py
pytoniq_tools/client/__init__.py
pytoniq_tools/client/_base.py
pytoniq_tools/client/lite.py
pytoniq_tools/client/tonapi.py
pytoniq_tools/client/toncenter.py
pytoniq_tools/jetton/__init__.py
pytoniq_tools/jetton/_base.py
pytoniq_tools/jetton/op_codes.py
pytoniq_tools/nft/__init__.py
pytoniq_tools/nft/content.py
pytoniq_tools/nft/data.py
pytoniq_tools/nft/op_codes.py
pytoniq_tools/nft/royalty_params.py
pytoniq_tools/nft/_base/__init__.py
pytoniq_tools/nft/_base/collection.py
pytoniq_tools/nft/_base/item.py
pytoniq_tools/nft/editable/__init__.py
pytoniq_tools/nft/editable/collection.py
pytoniq_tools/nft/editable/item.py
pytoniq_tools/nft/soulbound/__init__.py
pytoniq_tools/nft/soulbound/collection.py
pytoniq_tools/nft/soulbound/item.py
pytoniq_tools/nft/standard/__init__.py
pytoniq_tools/nft/standard/collection.py
pytoniq_tools/nft/standard/item.py
pytoniq_tools/wallet/__init__.py
pytoniq_tools/wallet/_base.py
pytoniq_tools/wallet/data.py
pytoniq_tools/wallet/version/__init__.py
pytoniq_tools/wallet/version/highload.py
pytoniq_tools/wallet/version/v3.py
pytoniq_tools/wallet/version/v4.py
pytoniq_tools-0.1.1.dist-info/LICENSE
pytoniq_tools-0.1.1.dist-info/METADATA
pytoniq_tools-0.1.1.dist-info/WHEEL
pytoniq_tools-0.1.1.dist-info/top_level.txt
pytoniq_tools-0.1.1.dist-info/RECORD
