Metadata-Version: 2.1
Name: pytoniq-tools
Version: 0.1.1
Summary: Pytoniq Tools is a high-level OOP library for Python designed for interacting with the TON. It is built on top of three of the most popular libraries for working with TON in Python: pytoniq, pytonapi, and pytoncenter.
Home-page: https://github.com/nessshon/pytoniq-tools/
Author: nessshon
Classifier: Programming Language :: Python :: 3.10
Classifier: Programming Language :: Python :: 3.11
Classifier: License :: OSI Approved :: MIT License
Classifier: Operating System :: OS Independent
License-File: LICENSE
Requires-Dist: pytoniq ~=0.1.39
Requires-Dist: pytoncenter ~=0.0.14
Requires-Dist: pytonapi ~=0.3.2
